sbr_odds_scraper/__init__.py
sbr_odds_scraper/api.py
sbr_odds_scraper/cli.py
sbr_odds_scraper/pools.py
sbr_odds_scraper/scraper.py
sbr_odds_scraper-0.1.4.dist-info/METADATA
sbr_odds_scraper-0.1.4.dist-info/WHEEL
sbr_odds_scraper-0.1.4.dist-info/entry_points.txt
sbr_odds_scraper-0.1.4.dist-info/top_level.txt
sbr_odds_scraper-0.1.4.dist-info/RECORD
