Metadata-Version: 2.4
Name: sbr-odds-scraper
Version: 0.1.4
Summary: A web scraper that collects historical MLB betting odds from SportsBookReview
Author: Arnav Saraogi
Maintainer-email: Oronto <vile319@gmail.com>
License-Expression: MIT
Project-URL: Homepage, https://github.com/ArnavSaraogi/mlb-odds-scraper
Project-URL: Bug Tracker, https://github.com/ArnavSaraogi/mlb-odds-scraper/issues
Project-URL: Source, https://github.com/ArnavSaraogi/mlb-odds-scraper
Keywords: mlb,baseball,odds,betting,scraper,sports
Classifier: Development Status :: 4 - Beta
Classifier: Intended Audience :: Developers
Classifier: Programming Language :: Python :: 3
Classifier: Programming Language :: Python :: 3.8
Classifier: Programming Language :: Python :: 3.9
Classifier: Programming Language :: Python :: 3.10
Classifier: Programming Language :: Python :: 3.11
Classifier: Programming Language :: Python :: 3.12
Classifier: Topic :: Internet :: WWW/HTTP :: Indexing/Search
Requires-Python: >=3.8
Requires-Dist: aiohttp>=3.8.0
Requires-Dist: requests>=2.25.0
Requires-Dist: tqdm>=4.60.0
Requires-Dist: pandas>=1.3.0
Requires-Dist: nest-asyncio>=1.5.0
